inteliquent/__init__.py
inteliquent/client.py
inteliquent/messaging.py
inteliquent/utils.py
tests/__init__.py
tests/test_client.py
inteliquent-0.3.1.dist-info/METADATA
inteliquent-0.3.1.dist-info/WHEEL
inteliquent-0.3.1.dist-info/top_level.txt
inteliquent-0.3.1.dist-info/RECORD
