Metadata-Version: 2.1
Name: inteliquent
Version: 0.3.1
Summary: Python bindings for Inteliquent, a versiatile telecommunications provider
Home-page: UNKNOWN
Author: Inteliquent
Author-email: tyler.hunt@inteliquent.com
License: UNKNOWN
Platform: UNKNOWN
Classifier: Development Status :: 2 - Pre-Alpha
Classifier: Programming Language :: Python :: 3
Classifier: Programming Language :: Python :: 3.5
Classifier: Programming Language :: Python :: 3.6
Classifier: Programming Language :: Python :: 3.7
Classifier: Programming Language :: Python :: 3.8
Requires-Python: >=3.5
Requires-Dist: requests
